llm_embed_gemini.py
llm_embed_gemini-0.1.4.dist-info/licenses/LICENSE
llm_embed_gemini-0.1.4.dist-info/METADATA
llm_embed_gemini-0.1.4.dist-info/WHEEL
llm_embed_gemini-0.1.4.dist-info/entry_points.txt
llm_embed_gemini-0.1.4.dist-info/top_level.txt
llm_embed_gemini-0.1.4.dist-info/RECORD
