Metadata-Version: 2.4
Name: llm-embed-gemini
Version: 0.1.4
Summary: Embedding models from Gemini
Author: Florents Tselai
License: Apache-2.0
Project-URL: Homepage, https://github.com/Florents-Tselai/llm-embed-gemini
Project-URL: Changelog, https://github.com/Florents-Tselai/llm-embed-gemini/releases
Project-URL: Issues, https://github.com/Florents-Tselai/llm-embed-gemini/issues
Project-URL: CI, https://github.com/Florents-Tselai/llm-embed-gemini/actions
Classifier: License :: OSI Approved :: Apache Software License
License-File: LICENSE
Requires-Dist: llm
Provides-Extra: test
Requires-Dist: pytest; extra == "test"
Dynamic: license-file
